LICENSE
MANIFEST.in
README.md
requirements.txt
setup.py
google_home_ui_automator.egg-info/PKG-INFO
google_home_ui_automator.egg-info/SOURCES.txt
google_home_ui_automator.egg-info/dependency_links.txt
google_home_ui_automator.egg-info/entry_points.txt
google_home_ui_automator.egg-info/requires.txt
google_home_ui_automator.egg-info/top_level.txt
ui_automator/__init__.py
ui_automator/android_device.py
ui_automator/android_device_test.py
ui_automator/commission_reg_test.py
ui_automator/errors.py
ui_automator/test_reporter.py
ui_automator/test_reporter_test.py
ui_automator/ui_automator.py
ui_automator/ui_automator_test.py
ui_automator/unit_test_utils.py
ui_automator/version.py
ui_automator/android/app/snippet.apk