Metadata-Version: 2.4
Name: google-home-ui-automator
Version: 1.0.5
Summary: Google Home UI Automator
Home-page: https://testsuite-smarthome-matter.googlesource.com/ui-automator/
Author: Google LLC
Author-email: google-home-testsuite-dev+ui-automator@google.com
License: Apache 2.0
Classifier: Development Status :: 5 - Production/Stable
Classifier: Intended Audience :: Developers
Classifier: License :: OSI Approved :: Apache Software License
Classifier: Operating System :: MacOS
Classifier: Operating System :: POSIX :: Linux
Classifier: Programming Language :: Python :: 3.11
Classifier: Programming Language :: Python :: 3.12
Classifier: Programming Language :: Python :: 3.13
Classifier: Topic :: Software Development :: Libraries :: Python Modules
Classifier: Topic :: Software Development :: Testing
Requires-Python: >=3.11
License-File: LICENSE
Requires-Dist: mobly==1.12
Requires-Dist: inflection
Requires-Dist: absl-py
Requires-Dist: immutabledict
Dynamic: author
Dynamic: author-email
Dynamic: classifier
Dynamic: description
Dynamic: description-content-type
Dynamic: home-page
Dynamic: license
Dynamic: license-file
Dynamic: requires-dist
Dynamic: requires-python
Dynamic: summary
